nb_autodoc/__init__.py
nb_autodoc/__main__.py
nb_autodoc/builders/__init__.py
nb_autodoc/builders/helpers.py
nb_autodoc/builders/markdown.py
nb_autodoc/builders/parser/__init__.py
nb_autodoc/builders/parser/google.py
nb_autodoc/pycode/__init__.py
nb_autodoc/pycode/overload.py
nb_autodoc/pycode/unparser.py
nb_autodoc/pycode/vcpicker.py
nb_autodoc/schema/__init__.py
nb_autodoc/schema/ast.py
nb_autodoc/schema/docstring.py
nb_autodoc/utils.py
nb_autodoc-0.1.0.dist-info/entry_points.txt
nb_autodoc-0.1.0.dist-info/WHEEL
nb_autodoc-0.1.0.dist-info/METADATA
nb_autodoc-0.1.0.dist-info/license_files/LICENSE
nb_autodoc-0.1.0.dist-info/RECORD
