Metadata-Version: 2.1
Name: nb-autodoc
Version: 0.1.0
Summary: API doc generator for NoneBot.
License: MIT
Keywords: nonebot,autodoc
Author-email: iyume <iyumelive@gmail.com>
Requires-Python: >=3.7
Requires-Dist: attrs~=21.4
Requires-Dist: click>=8.0.3
Requires-Dist: six>=1.6.1
Project-URL: documentation, https://github.com/nonebot/nb-autodoc/blob/master/README.md
Project-URL: homepage, https://github.com/nonebot/nb-autodoc
Project-URL: repository, https://github.com/nonebot/nb-autodoc
